{
  "no_apis": "沒有 API 可顯示。",
  "api_contact_email": "電子郵件",
  "api_contact_info": "聯絡",
  "api_contact_information": "聯絡資訊",
  "api_contact_name": "名稱",
  "api_contact_url": "URL",
  "description": "說明",
  "security": "安全",
  "expand_all": "全部展開",
  "collapse_all": "全部收合",
  "code": "代碼",
  "endpoint": "端點",
  "endpoints": "端點",
  "explorer_target_endpoint": "目標端點",
  "explorer_swagger_host": "使用 Open API 主機",
  "development": "開發",
  "production": "正式作業",
  "example": "範例",
  "summary": "摘要",
  "api_located_in": "{{type}} 位於 {{in}}",
  "bearer_format": "持有人格式",
  "required": "必要",
  "responses": "回應",
  "definition": "定義",
  "definitions": "定義",
  "operations": "作業",
  "body": "內文",
  "tags": "標籤",
  "search": "搜尋",
  "resize": "拖曳來調整大小",
  "scheme": "架構",
  "copy_to_clipboard": "複製目標到剪貼簿",
  "copied_to_clipboard": "已複製到剪貼簿",
  "view_operations_by": "檢視作業的依據：",
  "group_by_tags": "依標籤分組",
  "operations_by_summary": "摘要",
  "operations_by_path": "路徑",
  "operations_by_name": "名稱",
  "examples": "範例",
  "login": "登入以嘗試此 API",
  "try": "嘗試",
  "optional": "選用",
  "in_header": "位於標頭",
  "identification": "身分識別",
  "example_request": "範例要求",
  "explorer_no_apis": "沒有 API 可顯示。請建立一些模型和 API，點選執行，並回到這裡檢視並進行互動。",
  "explorer_failed_to_load_api": "從提供的 URL 載入 API 時發生錯誤。",
  "explorer_no_apis_found": "沒有 API 可顯示。",
  "accept": "接受",
  "content_type": "內容類型",
  "request": "要求",
  "response": "回應",
  "headers": "標頭",
  "authorization": "授權",
  "explorer_authorize": "授權",
  "explorer_showing_draft_apis": "伺服器似乎不在執行中，因此草稿 API 顯示於下方。如果想查看執行中的 API，請確定伺服器正在執行。",
  "response_code": "代碼",
  "response_time": "時間",
  "explorer_invalid_swagger": "無法載入選取的 API：",
  "explorer_check_certificate": "按下面的鏈結，將在新標籤中開啟伺服器。如果瀏覽器顯示憑證問題，您可以選擇接受它，然後回到這裡以重新測試。",
  "explorer_security_requirements": "呼叫 API 時，必須滿足下列其中一組需求",
  "explorer_additional_docs": "其他說明文件",
  "explorer_external_links": "外部鏈結",
  "documentation": "文件",
  "download_swagger": "下載 OpenAPI 文件",
  "download_api_doc": "下載 API 文件",
  "of": "之",
  "explorer_cors": "未收到回應。原因包括目標伺服器缺少 CORS 支援、伺服器無法使用，或發現未授信憑證。",
  "explorer_cors_mtls": "未收到回應。原因包括目標伺服器缺少 CORS 支援、伺服器無法使用、發現未授信憑證，或需要 SSL 交互鑑別。",
  "explorer_type_headers": "類型標頭",
  "explorer_apis": "API",
  "explorer_application": "應用程式",
  "explorer_products": "產品",
  "explorer_auth_code": "授權碼",
  "explorer_help_access_code": "依適當情況使用授權和記號 URL，以獲得用於此 OAuth 安全流程的存取記號，然後在這裡輸入存取記號。",
  "explorer_help_implicit": "依適當情況使用授權 URL，以獲得用於此 OAuth 安全流程的存取記號，然後在這裡輸入存取記號。",
  "explorer_access_token": "存取記號",
  "explorer_refresh_token": "重新整理記號",
  "explorer_refresh_url": "重新整理 URL",
  "explorer_get_token": "取得記號",
  "explorer_authorization_url": "授權 URL",
  "explorer_token_url": "記號 URL",
  "explorer_openIdConnect_url": "OpenID Connect URL",
  "explorer_oidc_discover": "探索",
  "explorer_scopes": "範圍",
  "explorer_scope": "範圍",
  "explorer_show_schema": "綱目",
  "explorer_show_example": "範例",
  "explorer_redirect_uri": "重新導向 URI",
  "name": "名稱",
  "type": "類型",
  "terms_of_service": "服務條款",
  "terms_of_service_link": "檢視服務條款",
  "parameter": "參數",
  "parameters": "參數",
  "schema": "綱目",
  "client_id": "API 金鑰",
  "client_secret": "API 密碼",
  "public": "公開",
  "confidential": "機密",
  "implicit": "隱含",
  "application": "應用程式",
  "access_code": "存取碼",
  "explorer_client_type": "用戶端類型",
  "explorer_security_flow": "安全流程",
  "username": "使用者名稱",
  "password": "密碼",
  "assembly_show_schema": "顯示綱目",
  "assembly_generate_data": "產生",
  "assembly_generate_default_object": "產生物件",
  "deprecated": "已淘汰",
  "operation_deprecated": "此作業已淘汰",
  "devportal_not_logged_in": "請登入您的帳戶，以查看您的可用應用程式。",
  "devportal_sign_in": "登入",
  "devportal_no_apps": "您沒有任何應用程式。",
  "devportal_create_app": "建立應用程式",
  "menu": "功能表",
  "collapse_toggle": "收合畫面",
  "expand_toggle": "展開畫面",
  "details_header": "詳細資料",
  "events_header": "事件",
  "event": "事件",
  "event_topic": "主題",
  "security_option": "選項",
  "security_option_label": "安全選項 {{number}}",
  "security_options": "安全選項",
  "overview": "概觀",
  "query": "查詢",
  "path": "路徑",
  "header": "標頭",
  "form_data": "表單資料",
  "cookie": "Cookie",
  "possible_values": "允許值",
  "reset": "重設",
  "send": "傳送",
  "no_endpoint": "未指定端點",
  "more": "更多",
  "less": "更少",
  "show_more": "顯示更多",
  "show_less": "顯示更少",
  "mixedcontent_error": "沒有回應。這是混合內容呼叫。不可能從經由 HTTPS 提供的頁面來呼叫 HTTP 端點。",
  "invalid_client": "未獲授權。請確定您已針對上方所訂閱的應用程式，指定 API 金鑰和密碼。",
  "invalid_scope": "未獲授權。無效的範圍。",
  "invalid_grant": "未獲授權。無效的授權。",
  "access_denied": "找不到或拒絕了資源擁有者",
  "generic_invoke_error": "錯誤。發生錯誤。請查看瀏覽器開發人員工具，以取得詳細資料。",
  "404_not_found": "404 - 找不到。沒有資源符合所要求的 URI",
  "api_extensions": "API 延伸項目",
  "info_extensions": "API 資訊延伸項目",
  "extensions": "延伸",
  "register_app": "登錄應用程式以測試此 API",
  "copy_as_curl": "複製成 cURL",
  "x_client_certficate_header": "您應用程式的 TLS 憑證",
  "choose_file": "選擇檔案",
  "response_headers": "回應標頭",
  "response_body": "回應內文",
  "response_extensions": "回應延伸項目",
  "response_links": "回應鏈結",
  "other": "其他",
  "swagger_errors": "Open API 驗證錯誤",
  "swagger_errors_description": "Open API 文件不符合 OAI 規格。",
  "close_swagger_errors": "隱藏 Open API 驗證錯誤通知",
  "swagger_validation_size_warning": "龐大的 Open API 文件",
  "swagger_validation_size_warning_description": "此 Open API 很大。已跳過驗證，因為這可能導致您的瀏覽器不穩定。",
  "swagger_validation_size_override": "還是要嘗試驗證嗎？",
  "filter": "過濾",
  "filter_options": "過濾選項",
  "filter_menu": "過濾器功能表",
  "generator_error": "無法產生範例資料。所報告的錯誤是：'{{error}}'",
  "on": "開啟",
  "off": "關閉",
  "apic_connect_apis": "API Connect REST API",
  "error": "錯誤",
  "enabled": "已啟用",
  "mutual_tls": "相互 TLS",
  "realm": "領域",
  "nonce": "暫時性要求",
  "opaque": "不透明",
  "version": "版本",
  "session_identifier": "階段作業 ID",
  "verification_value": "驗證值",
  "signature": "簽章",
  "signature_method": "簽章方法",
  "challenge": "盤查",
  "key_identifier": "金鑰 ID",
  "gssapi_data": "GSS-API 資料",
  "consumer_key": "消費者金鑰",
  "token": "記號",
  "timestamp": "時間戳記",
  "json_web_token": "JSON Web 記號",
  "json_web_key": "JSON Web 金鑰",
  "encrypted_creds": "加密認證",
  "example_payload": "有效負載範例",
  "channel_publish_operation": "{{channelName}} 發佈（作業）",
  "channel_subscribe_operation": "{{channelName}} 訂閱（作業）",
  "payload_schema": "有效負載綱目",
  "invalid_schema": "綱目無效，或沒有提供綱目",
  "menu_button": "功能表展開及收合按鈕",
  "something_went_wrong": "發生錯誤！",
  "dont_know_how_to_display": "不知道如何顯示 '{{display}}' 類型",
  "channel_overview_label": "通道名稱",
  "channel_overview_consume": "如何耗用",
  "channel_overview_description": "說明",
  "channel_overview_subscribe": "訂閱（作業）",
  "channel_overview_publish": "發佈（作業）",
  "channel_overview_title": "概觀",
  "channel_overview_error": "通道資料無效",
  "channel_overview_error_label": "無法顯示通道",
  "code_snippet_label": "程式碼 Snippet",
  "code_snippet_language_label": "Snippet 語言",
  "unsupported_schema_format": "不受支援的綱目格式：{{schemaFormat}}",
  "message_stream": "{{channelName}} 訊息串流",
  "channel_publish_menu": "發佈（作業）",
  "channel_subscribe_menu": "訂閱（作業）",
  "download_asyncapi": "下載 AsyncAPI 文件",
  "download_icon": "「下載」圖示",
  "download_schema": "下載綱目",
  "example_generator_no_schema_error": "找不到要從中產生範例的綱目。",
  "example_generator_error": "產生範例時發生錯誤：{{ error }}",
  "protocol": "通訊協定",
  "SASL_secure": "Kafka 叢集受 SASL 的保護，如需使用哪個 SASL 通訊協定的相關資訊，請聯絡 API 擁有者。",
  "SSL_secure": "Kafka 叢集已啟用加密。請聯絡 API 擁有者以取得適當的信任儲存庫及用戶端金鑰儲存庫配置。",
  "unknown_secure": "Kafka 叢集受保護，請聯絡 API 擁有者以取得認證。",
  "contact_api_owner": "API 擁有者未提供所有必要值，請聯絡擁有者以取得正確的值",
  "async_parse_errors": "AsyncAPI 驗證錯誤",
  "async_parse_errors_description": "AsyncAPI 文件不符合規格。",
  "do_something_avro": "處理您的記錄",
  "do_something_default": "處理您的值",
  "truststore_warning": "Kafka 叢集可能已啟用加密。請聯絡 API 擁有者以取得適當的信任儲存庫配置。",
  "tls_version_warning": "請聯絡 API 擁有者以找出應該使用的 TLS 版本。",
  "async_doc_link_title": "檢視 AsyncAPI 文件的相關資訊",
  "kafka_doc_link_title": "檢視 Kafka 通訊協定的相關資訊",
  "do_something_asyncapi": "處理您的 JSON 資料",
  "custom_deserializer_class": "custom_deserializer_class",
  "kafka_key_help": "請聯絡 API 擁有者以取得如何對此類別解除序列的相關資訊",
  "error_404": "錯誤 404。找不到頁面",
  "request_security_credentials": "存取此 API 需要安全認證。 請聯絡管理者以取得詳細資料。",
  "invalid_JSON_example": "提供的範例不是有效的 JSON：{{ errormsg }}",
  "asyncApi_payload_generation_error": "產生 AsyncAPI 範例有效負載時發生錯誤：{{ errormsg }}",
  "no_examples": "文件中未提供任何範例",
  "application_credentials": "應用程式認證",
  "credential_number": "認證 {{ credential_number }}",
  "app_number": "應用程式 {{ app_number }}",
  "received": "已接收",
  "sent": "已傳送",
  "waiting_connection": "正在等待連線...",
  "connected": "已連接",
  "connection_error": "連線錯誤",
  "connection_closed": "連線已關閉",
  "enter_message": "輸入您的訊息",
  "connect_failed": "無法連接",
  "status": "狀態",
  "message_log": "訊息日誌",
  "callbacks": "回呼",
  "connect": "連接",
  "message": "訊息",
  "disconnect": "中斷連線",
  "server_variables": "伺服器變數",
  "insert_sasl_password": "SASL_password",
  "enter_client_id": "輸入您自己的 API 金鑰",
  "model_label": "其他文件限制模式",
  "properties": "內容",
  "key": "金鑰",
  "value": "值",
  "instructions": "指示",
  "references": "參照",
  "encrypted_protocol": "{{ protocol }}（已加密）",
  "header_schema": "標頭綱目",
  "placeholder_values": "顯示內容的位置保留元值。",
  "login_to_use": "位置保留元值會一直顯示，直到您登入並存取此 API 為止。",
  "login_to_use_with_link": "位置保留元值會一直顯示，直到您<0>登入</0>並存取此 API 為止。",
  "get_access_to_use": "位置保留元值會一直顯示，直到您存取此 API 為止。",
  "login_link_title": "登入 Developer Portal",
  "login_link_text": "登入",
  "app_no_access": "找不到具有存取權的應用程式",
  "subscribed_creds_explanation": "只能選取已訂閱的認證。",
  "reserved_title": "使用中的保留標頭",
  "reserved_subtitle": "此 API 使用不會隨要求一起傳送的保留標頭。",
  "title": "標題",
  "contents": "內容",
  "channel_publish_description": "含有內容綱目參照的發佈指示。",
  "channel_subscribe_description": "包含有效負載綱目參照的使用指示。",
  "operation": "作業",
  "copy_client_id": "複製用戶端 ID",
  "dependencies": "相依關係",
  "binding_details": "連結詳細資料"
}